{
  "data": {
    "chapter_path": "/books/nahj-al-balagha:3:379",
    "chapter_title": {
      "en": "Choosing between revenge and forgiveness when angry"
    },
    "nav": {
      "up": "/books/nahj-al-balagha:3:379"
    },
    "source_url": "https://thaqalayn.net/hadith/32/3/194/240",
    "verse": {
      "index": 2137,
      "local_index": 1,
      "part_type": "Hadith",
      "path": "/books/nahj-al-balagha:3:379:1",
      "relations": null,
      "source_url": "https://thaqalayn.net/hadith/32/3/194/240",
      "text": [
        "١٩٤. وكان (عليه ‏السلام) يقول: مَتَى أَشْفِي غَيْظِي إِذَا غَضِبْتُ؟ أَحِينَ أَعْجِزُ عَنِ الِانْتِقَامِ فَيُقَالُ لِي: لَوْ صَبَرْتَ؟ أَمْ حِينَ أَقْدِرُ عَلَيْهِ فَيُقَالُ لي: لَوْ عَفَوْتَ."
      ],
      "translations": {
        "en.sayed-ali-raza": [
          "194. Amīr al-mu’minīn, peace be upon him, used to say: If I am angry when shall I vent my anger - when I am unable to take revenge and it be said to me, “better you endure” or when I have power to take revenge and it be said to me, “better forgive”?"
        ]
      }
    }
  },
  "index": "nahj-al-balagha:3:379:1",
  "kind": "verse_detail"
}