{
  "data": {
    "chapter_path": "/books/al-khisal:4:203",
    "chapter_title": {
      "en": "The Three Reasons Why People Worship God"
    },
    "nav": {
      "up": "/books/al-khisal:4:203"
    },
    "source_url": "https://thaqalayn.net/hadith/10/4/203/1",
    "verse": {
      "index": 501,
      "local_index": 1,
      "narrator_chain": {
        "parts": [
          {
            "kind": "plain",
            "text": "3-259 "
          },
          {
            "kind": "plain",
            "text": "حدثنا محمد بن أحمد السناني المكتب رضي الله عنه قال"
          }
        ]
      },
      "part_type": "Hadith",
      "path": "/books/al-khisal:4:203:1",
      "source_url": "https://thaqalayn.net/hadith/10/4/203/1",
      "text": [
        ": حدثنا محمد بن هارون الصوفي قال: حدثنا عبيد الله بن موسى الحبال الطبري قال: حدثنا محمد بن الحسين الخشاب قال: حدثنا محمد بن محصن، عن يونس بن ظبيان قال: قال الصادق جعفر بن محمد عليهما السلام: إن الناس يعبدون الله عز وجل على ثلاثة أوجه، فطبقة يعبدونه رغبة في ثوابه فتلك عبادة الحرصاء وهو الطمـع، وآخـرونيعبدونه فرقا من النار فتلك عبادة العبيد وهي الرهبة، ولكني أعبده حبا له عز وجل فتلك عبادة الكرام وهو الامن لقوله عز وجل \"وهم من فزع يومئذ آمنون\" ولقوله عز وجل \"قل إن كنتم تحبون الله فاتبعوني يحببكم الله ويغفر لكم ذنوبكم\" فمن أحب الله أحبه الله عز وجل، ومن أحبه الله عز وجل كان من الآمنين"
      ],
      "translations": {
        "en.dr-ali-peiravi": [
          "3-259 Muhammad ibn Ahmad al-Senani al-Mokattib - may God be pleased with him - narrated that Muhammad ibn Harun al-Soofi quoted Ubaydullah ibn Musa al-Hibal al-Tabary, on the authority of Muhammad ibn al-Hussein al-Khisahab, on the authority of Muhammad ibn Mohsin, on the authority of Yunus ibn Zabyan that Ja’far ibn Muhammad as-Sadiq (MGB) said, “There are three reasons why the people worship the Exalted the Honorable God. Some worship God in order to receive a reward. Such form of worship is that of greedy people. Some worship God out of fear ofthe Fire. Such form of worship is due to fear. I worship God since I love the Exalted the Honorable God. Such form of worship is that of noble ones. There is security in it as stated by the Honorable the Exalted God, ‘… and they will be secure from terror that Day’ and ‘Say: If ye do love God, Follow me: God will love you and forgive you your sins: ….’ Therefore, the Exalted the Honorable God loves whomever loves God. Whoever the Honorable the Exalted God loves is amongst the secure ones.”"
        ]
      }
    },
    "verse_translations": [
      "en.dr-ali-peiravi"
    ]
  },
  "index": "al-khisal:4:203:1",
  "kind": "verse_detail"
}