{
  "data": {
    "chapter_path": "/books/al-kafi:2:2:52",
    "chapter_title": {
      "ar": "بَابُ الدُّعَاءِ فِي أَدْبَارِ الصَّلَوَاتِ",
      "en": "Chapter 52 – The supplication at the end of the Salāt"
    },
    "gradings": [
      "Allamah Baqir al-Majlisi: <span> حسن كالصحيح    </span> - Mir‘at al ‘Uqul Fi Sharh Akhbar Al al Rasul (12/335)"
    ],
    "nav": {
      "next": "/books/al-kafi:2:2:52:2",
      "up": "/books/al-kafi:2:2:52"
    },
    "verse": {
      "gradings": [
        "Allamah Baqir al-Majlisi: <span> حسن كالصحيح    </span> - Mir‘at al ‘Uqul Fi Sharh Akhbar Al al Rasul (12/335)"
      ],
      "index": 3360,
      "local_index": 1,
      "narrator_chain": {
        "parts": [
          {
            "kind": "narrator",
            "path": "/people/narrators/4",
            "text": "مُحَمَّدُ بْنُ يَحْيَى"
          },
          {
            "kind": "plain",
            "text": " عَنْ "
          },
          {
            "kind": "narrator",
            "path": "/people/narrators/13",
            "text": "أَحْمَدَ بْنِ مُحَمَّدِ بْنِ عِيسَى"
          },
          {
            "kind": "plain",
            "text": " عَنْ "
          },
          {
            "kind": "narrator",
            "path": "/people/narrators/501",
            "text": "أَبِي عَبْدِ اللَّهِ الْبَرْقِيِّ"
          },
          {
            "kind": "plain",
            "text": " عَنْ "
          },
          {
            "kind": "narrator",
            "path": "/people/narrators/940",
            "text": "عِيسَى بْنِ عَبْدِ اللَّهِ الْقُمِّيِّ"
          },
          {
            "kind": "plain",
            "text": " عَنْ "
          },
          {
            "kind": "narrator",
            "path": "/people/narrators/1",
            "text": "أَبِي عَبْدِ اللَّهِ ( عليه السلام )"
          },
          {
            "kind": "plain",
            "text": " قَالَ"
          }
        ]
      },
      "part_type": "Hadith",
      "path": "/books/al-kafi:2:2:52:1",
      "text": [
        " كَانَ أَمِيرُ الْمُؤْمِنِينَ ( صلوات الله عليه )  يَقُولُ إِذَا فَرَغَ مِنَ الزَّوَالِ اللَّهُمَّ إِنِّي أَتَقَرَّبُ إِلَيْكَ بِجُودِكَ وَ كَرَمِكَ وَ أَتَقَرَّبُ إِلَيْكَ بِمُحَمَّدٍ عَبْدِكَ وَ رَسُولِكَ وَ أَتَقَرَّبُ إِلَيْكَ بِمَلَائِكَتِكَ الْمُقَرَّبِينَ وَ أَنْبِيَائِكَ الْمُرْسَلِينَ وَ بِكَ ",
        "اللَّهُمَّ أَنْتَ الْغَنِيُّ عَنِّي وَ بِيَ الْفَاقَةُ إِلَيْكَ أَنْتَ الْغَنِيُّ وَ أَنَا الْفَقِيرُ إِلَيْكَ أَقَلْتَنِي عَثْرَتِي وَ سَتَرْتَ عَلَيَّ ذُنُوبِي فَاقْضِ لِيَ الْيَوْمَ حَاجَتِي وَ لَا تُعَذِّبْنِي بِقَبِيحِ مَا تَعْلَمُ مِنِّي بَلْ عَفْوُكَ وَ جُودُكَ يَسَعُنِي ",
        "قَالَ ثُمَّ يَخِرُّ سَاجِداً وَ يَقُولُ يَا أَهْلَ التَّقْوَى وَ يَا أَهْلَ الْمَغْفِرَةِ يَا بَرُّ يَا رَحِيمُ أَنْتَ أَبَرُّ بِي مِنْ أَبِي وَ أُمِّي وَ مِنْ جَمِيعِ الْخَلَائِقِ اقْبَلْنِي بِقَضَاءِ حَاجَتِي مُجَاباً دُعَائِي مَرْحُوماً صَوْتِي قَدْ كَشَفْتَ أَنْوَاعَ الْبَلَايَا عَنِّي ."
      ],
      "translations": {
        "en.hubeali": [
          "Muhammad Bin Yahya, from Ahmad Bin Muhammad Bin Isa, from Abu Abdullah Al Narqy, from Isa Bin Abdullah Al Qummy, ",
          "(It has been narrated) from Abu Abdullah<sup>asws</sup> having said: ‘Amir Al-<span class=\"iTxt\">Momin</span>een<sup>asws</sup> was saying whenever he<sup>asws</sup> was free from the decline (midday <span class=\"iTxt\">Salāt</span>): ‘O Allah<sup>azwj</sup>! I<sup>asws</sup> come closer to You<sup>azwj</sup> by Your<sup>azwj</sup> Generosity and Your<sup>azwj</sup> Benevolence, and I<sup>asws</sup> come closer to You<sup>azwj</sup> by Muhammad<sup>azwj</sup> Your<sup>azwj</sup> servant and Your<sup>azwj</sup> Rasool<sup>saww</sup>, and I<sup>asws</sup> come closer to You<sup>azwj</sup> by Your<sup>azwj</sup> Angels of Proximity, and Your<sup>azwj</sup> Prophets<sup>as</sup>, the <span class=\"iTxt\">Mursileen</span>, and By You<sup>azwj</sup>.",
          "O Allah<sup>azwj</sup>! You<sup>azwj</sup> are the One Needless from me, and with me is the need (requirement) to You<sup>azwj</sup>. You<sup>saww</sup> are the rich and I am the poor to You<sup>azwj</sup>. You<sup>azwj</sup> Discharge my traces (of errors), and Veil my sins upon me. So Fulfil my needs for me today and do not Punish me with ugliness what You<sup>azwj</sup> are more Knowing of than I am. But, Amplify upon me, Your<sup>azwj</sup> Pardon and Your<sup>azwj</sup> generosity’. ",
          "He<sup style=\"font-weight: normal\">asws</sup> said: ‘Then he<sup style=\"font-weight: normal\">asws</sup> would perform Sajdah and he<sup style=\"font-weight: normal\">asws</sup> would be saying: ‘O the One rightful to be feared, and O the One rightful for the Forgiveness, O Righteous, O Merciful! You<sup style=\"font-weight: normal\">azwj</sup> are more Righteous with me than my father and my mother, and from the entirety of the creatures. Accept me by Fulfilling my need by Answering my supplication, Merciful upon my voice as You<sup style=\"font-weight: normal\">azwj</sup> have Removed a variety of the afflictions from me’’."
        ],
        "en.sarwar": [
          "1. Muhammad ibn Yahya has narrated from Ahmad ibn Muhammad ibn ‘Isa from abu ‘Abd Allah al-Barqi from ‘Isa ibn ‘Abd Allah al-Qummi from abu ‘Abd Allah (a.s.) who has said the following: “Amir al-Mu’minin, Ali ibn abu Talib (a.s.) after completing the prayer at noon time would say, ‘O Lord, I seek nearness to You through Your generosity and magnanimity, I seek nearness to You through Muhammad, Your servant, and Your messenger, I seek nearness to You through Your favorite angels. Your messenger prophets and Your Own Self. O Lord, You are Self-sufficient and do not need me and I need You. You are wealthy and I am poor, correct my slips (mistakes) and cover up my sins, provide me help this day, do not punish me for the evil that You know of me, but pardon me and Your munificence may encompass me.’ The Imam said, ‘Then he would prostrate and say, “O You Who deserves people’s observing piety before Him, O You Who grants forgiveness, O Virtuous, and O Merciful, You are more kind to me than my father and mother and all the creatures, accept my plea in providing me help, answering my supplication and prayer, grant me favor for my call while You have already removed so many misfortunes from me.’” "
        ]
      }
    },
    "verse_translations": [
      "en.hubeali",
      "en.sarwar"
    ]
  },
  "index": "al-kafi:2:2:52:1",
  "kind": "verse_detail"
}