{
  "data": {
    "chapter_path": "/books/al-kafi:5:2:149",
    "chapter_title": {
      "ar": "باب الضِّرَارِ ",
      "en": "Chapter 148 – The Damages"
    },
    "gradings": [
      "Allamah Baqir al-Majlisi: <span> ضعيف كالموثق  </span> - Mir‘at al ‘Uqul Fi Sharh Akhbar Al al Rasul (9/394)"
    ],
    "nav": {
      "next": "/books/al-kafi:5:2:149:2",
      "up": "/books/al-kafi:5:2:149"
    },
    "verse": {
      "gradings": [
        "Allamah Baqir al-Majlisi: <span> ضعيف كالموثق  </span> - Mir‘at al ‘Uqul Fi Sharh Akhbar Al al Rasul (9/394)"
      ],
      "index": 9301,
      "local_index": 1,
      "narrator_chain": {
        "parts": [
          {
            "kind": "narrator",
            "path": "/people/narrators/20",
            "text": "مُحَمَّدُ بْنُ يَحْيَى"
          },
          {
            "kind": "plain",
            "text": " عَنْ "
          },
          {
            "kind": "narrator",
            "path": "/people/narrators/4",
            "text": "أَحْمَدَ بْنِ مُحَمَّدٍ"
          },
          {
            "kind": "plain",
            "text": " عَنْ "
          },
          {
            "kind": "narrator",
            "path": "/people/narrators/241",
            "text": "مُحَمَّدِ بْنِ يَحْيَى"
          },
          {
            "kind": "plain",
            "text": " عَنْ "
          },
          {
            "kind": "narrator",
            "path": "/people/narrators/200",
            "text": "طَلْحَةَ بْنِ زَيْدٍ"
          },
          {
            "kind": "plain",
            "text": " عَنْ "
          },
          {
            "kind": "narrator",
            "path": "/people/narrators/19",
            "text": "أَبِي عَبْدِ اللَّهِ ( عليه السلام )"
          },
          {
            "kind": "plain",
            "text": " قَالَ"
          }
        ]
      },
      "part_type": "Hadith",
      "path": "/books/al-kafi:5:2:149:1",
      "relations": null,
      "text": [
        " إِنَّ الْجَارَ كَالنَّفْسِ غَيْرُ مُضَارٍّ وَ لَا آثِمٍ ."
      ],
      "translations": {
        "en.hubeali": [
          "Muhammad Bin Yahya, from Ahmad Bin Muhammad, from Muhammad Bin Yahya, from Talha Bin Zayd, ",
          "from Abu Abdullah<sup>asws</sup> having said: ‘The neighbour is like the self, without having caused harm nor a sin (fault)’."
        ],
        "en.sarwar": [
          "1. Muhammad ibn Yahya has narrated from Ahmad ibn Muhammad from Muhammad ibn Yahya from Talhah ibn Zayd who has said the following: “Abu ‘ Abd Allah, ‘Alayhi al-Salam, has said, ‘A neighbor (in matters of immunity) is like a soul which is not harmed or has not committed sins.’” "
        ]
      }
    }
  },
  "index": "al-kafi:5:2:149:1",
  "kind": "verse_detail"
}