{
  "data": {
    "chapter_path": "/books/tahdhib-al-ahkam:9:42",
    "chapter_title": {
      "ar": "44 - بَابُ مِيرَاثِ مَنْ لاَ وَارِثَ لَهُ مِنَ اَلْعَصَبَةِ وَ اَلْمَوَالِي وَ ذَوِي اَلْأَرْحَامِ"
    },
    "nav": {
      "next": "/books/tahdhib-al-ahkam:9:42:2",
      "up": "/books/tahdhib-al-ahkam:9:42"
    },
    "verse": {
      "index": 12022,
      "local_index": 1,
      "part_type": "Hadith",
      "path": "/books/tahdhib-al-ahkam:9:42:1",
      "text": [
        "اَلْحَسَنُ بْنُ مُحَمَّدِ بْنِ سَمَاعَةَ عَنِ اَلْحُسَيْنِ بْنِ هَاشِمٍ عَنِ اِبْنِ مُسْكَانَ عَنِ اَلْحَلَبِيِّ عَنْ أَبِي عَبْدِ اَللَّهِ عَلَيْهِ اَلسَّلاَمُ قَالَ : ««يَسْئَلُونَكَ عَنِ اَلْأَنْفالِ » » قَالَ «مَنْ مَاتَ وَ لَيْسَ لَهُ مَوْلًى فَمَالُهُ مِنَ اَلْأَنْفَالِ »."
      ]
    }
  },
  "index": "tahdhib-al-ahkam:9:42:1",
  "kind": "verse_detail"
}