{
  "data": {
    "chapter_path": "/books/al-khisal:3:98",
    "chapter_title": {
      "en": "The Prophet (sw) Was Pleased by Two Things"
    },
    "nav": {
      "up": "/books/al-khisal:3:98"
    },
    "source_url": "https://thaqalayn.net/hadith/10/3/98/1",
    "verse": {
      "index": 235,
      "local_index": 1,
      "narrator_chain": {
        "parts": [
          {
            "kind": "plain",
            "text": "2-121 "
          },
          {
            "kind": "plain",
            "text": "حدثنا الحسن بن محمد بن يحيى العلوي رضي الله عنه قال"
          }
        ]
      },
      "part_type": "Hadith",
      "path": "/books/al-khisal:3:98:1",
      "source_url": "https://thaqalayn.net/hadith/10/3/98/1",
      "text": [
        ": حدثني جدي قال: حدثنا داود بن القاسم قال: حدثنا الحسن بن زيد قال: سمعت جماعة من أهل بيتي يقولون: إن جعفر بن أبي طالب رضي الله عنه لما قدم من أرض الحبشة وكان بها مهاجرا وذلك يوم فتح خيبر، قام إليه النبي صلى الله عليه وآله فقبل بين عينيه ثم قال: ما أدري بأيهما أنا أسر: بقدوم جعفر، أو بفتح خيبر. وقد أخرجت الاخبار التي رويتها في هذا المعنى في كتاب فضائل جعفر بن أبي طالب عليه السلام"
      ],
      "translations": {
        "en.dr-ali-peiravi": [
          "2-121 Al-Hassan ibn Muhammad ibn Yahya al-Alavi - may God be pleased with him - narrated that his grandfather quoted on the authority of Davood ibn al-Qasim, on the authority of Al-Hassan ibn Zayd that he had heard a group of the members of his household say, “When Ja’far ibn Abi Talib - may God be pleased with him - returned from Ethiopia where he had migrated to, it coincided with the conquering of Khaybar. The Prophet (MGB) stood up in front of him, kissed him on the forehead and said, ‘I do not know what has pleased me more? Is it the return of Ja’far or is it the conquering of Khaybar by God.’”(The compiler of the book said,) ‘I have narrated the traditions in this regard in the book Faza’el Ja’far ibn Abi Talib."
        ]
      }
    },
    "verse_translations": [
      "en.dr-ali-peiravi"
    ]
  },
  "index": "al-khisal:3:98:1",
  "kind": "verse_detail"
}