{
  "data": {
    "index": 1332,
    "local_index": 120,
    "nav": {
      "next": "/books/al-kafi:5:2:121",
      "prev": "/books/al-kafi:5:2:119",
      "up": "/books/al-kafi:5:2"
    },
    "part_type": "Chapter",
    "path": "/books/al-kafi:5:2:120",
    "titles": {
      "ar": "<span class=\"first-scene-phrase\"><span class=\"first-in-scene\">ب</span>اب الرَّجُلِ يُعْطِي</span> الدَّرَاهِمَ ثُمَّ يَأْخُذُهَا بِبَلَدٍ آخَرَ",
      "en": "Chapter 119 – The man gives the Dirhams, then takes them in another city"
    },
    "verse_count": 3,
    "verse_refs": [
      {
        "local_index": 1,
        "part_type": "Hadith",
        "path": "/books/al-kafi:5:2:120:1"
      },
      {
        "local_index": 2,
        "part_type": "Hadith",
        "path": "/books/al-kafi:5:2:120:2"
      },
      {
        "local_index": 3,
        "part_type": "Hadith",
        "path": "/books/al-kafi:5:2:120:3"
      }
    ],
    "verse_start_index": 9148,
    "verse_translations": [
      "en.hubeali",
      "en.sarwar"
    ]
  },
  "index": "al-kafi:5:2:120",
  "kind": "verse_list"
}