{
  "data": {
    "chapter_path": "/books/al-kafi:4:1:37",
    "chapter_title": {
      "ar": "بَابُ النَّوَادِرِ",
      "en": "Chapter 84 – The Miscellaneous"
    },
    "gradings": [
      "Allamah Baqir al-Majlisi: <span> مرسل  </span> - Mir‘at al ‘Uqul Fi Sharh Akhbar Al al Rasul (6/178)"
    ],
    "nav": {
      "next": "/books/al-kafi:4:1:37:12",
      "prev": "/books/al-kafi:4:1:37:10",
      "up": "/books/al-kafi:4:1:37"
    },
    "verse": {
      "gradings": [
        "Allamah Baqir al-Majlisi: <span> مرسل  </span> - Mir‘at al ‘Uqul Fi Sharh Akhbar Al al Rasul (6/178)"
      ],
      "index": 6186,
      "local_index": 11,
      "narrator_chain": {
        "parts": [
          {
            "kind": "narrator",
            "path": "/people/narrators/6",
            "text": "عِدَّةٌ مِنْ أَصْحَابِنَا"
          },
          {
            "kind": "plain",
            "text": " عَنْ "
          },
          {
            "kind": "narrator",
            "path": "/people/narrators/12",
            "text": "أَحْمَدَ بْنِ مُحَمَّدِ بْنِ خَالِدٍ"
          },
          {
            "kind": "plain",
            "text": " عَنْ "
          },
          {
            "kind": "narrator",
            "path": "/people/narrators/41",
            "text": "عُثْمَانَ بْنِ عِيسَى"
          },
          {
            "kind": "plain",
            "text": " عَنْ "
          },
          {
            "kind": "narrator",
            "path": "/people/narrators/60",
            "text": "رَجُلٍ"
          },
          {
            "kind": "plain",
            "text": " عَنْ "
          },
          {
            "kind": "narrator",
            "path": "/people/narrators/1",
            "text": "أَبِي عَبْدِ اللَّهِ ( عليه السلام )"
          },
          {
            "kind": "plain",
            "text": " قَالَ"
          }
        ]
      },
      "part_type": "Hadith",
      "path": "/books/al-kafi:4:1:37:11",
      "text": [
        " جَاءَ رَجُلٌ إِلَى النَّبِيِّ ( صلى الله عليه وآله ) فَقَالَ إِنِّي شَيْخٌ كَثِيرُ الْعِيَالِ ضَعِيفُ الرُّكْنِ قَلِيلُ الشَّيْ‏ءِ فَهَلْ مِنْ مَعُونَةٍ عَلَى زَمَانِي فَنَظَرَ رَسُولُ اللَّهِ ( صلى الله عليه وآله ) إِلَى أَصْحَابِهِ وَ نَظَرَ إِلَيْهِ أَصْحَابُهُ وَ قَالَ قَدْ أَسْمَعَنَا الْقَوْلَ وَ أَسْمَعَكُمْ فَقَامَ إِلَيْهِ رَجُلٌ فَقَالَ كُنْتُ مِثْلَكَ بِالْأَمْسِ فَذَهَبَ بِهِ إِلَى مَنْزِلِهِ فَأَعْطَاهُ مِرْوَداً مِنْ تِبْرٍ وَ كَانُوا يَتَبَايَعُونَ بِالتِّبْرِ وَ هُوَ الذَّهَبُ وَ الْفِضَّةُ فَقَالَ الشَّيْخُ هَذَا كُلُّهُ قَالَ نَعَمْ فَقَالَ الشَّيْخُ أَقْبَلُ تِبْرَكَ فَإِنِّي لَسْتُ بِجِنِّيٍّ وَ لَا إِنْسِيٍّ وَ لَكِنِّي رَسُولٌ مِنَ اللَّهِ لِأَبْلُوَكَ فَوَجَدْتُكَ شَاكِراً فَجَزَاكَ اللَّهُ خَيْراً ."
      ],
      "translations": {
        "en.hubeali": [
          "A number of our companions, from Ahmad Bin Muhammad Bin Khalid, from Usman Bin Isa, from a man, ",
          "(It has been narrated) from Abu Abdullah<sup>asws</sup> having said: ‘A man came over to the Prophet<sup>saww</sup>, so he said: ‘I am an old man with a lot of dependants, weak of health, with few things. So, is there an assistance upon my time?’ So Rasool-Allah<sup>saww</sup> looked at his<sup>saww</sup> companions, and his<sup>saww</sup> companions looked at him<sup>saww</sup> and he<sup>saww</sup> said, ‘He made us<sup>saww</sup> to hear the speech, and made you all to hear it’. So a man stood up and he said, ‘I was like you yesterday’. So he went away with him to his house and gave him an ingot, and they used to be trading with the ingot, and it was the gold and the silver. So the old man said, ‘This is all of it (for me)?’ He said, ‘Yes’. So the old man said, ‘I accept your ingot, and I am neither a jinn nor a human, but I am a Messenger from Allah<sup>azwj</sup> to test you, so you have been found to be grateful. May Allah<sup>azwj</sup> Recompense you goodly’."
        ],
        "en.sarwar": [
          "11. A number of our people have narrated from Ahmad ibn Muhammad ibn Khalid from ‘Uthman ibn ‘Isa from a man who has said the following: “Abu ‘ Abd Allah, ‘Alayhi al-Salam, has said that once a man came to the Holy Prophet, O Allah, grant compensation to Muhammad and his family worthy of their services to Your cause, and said, ‘I am an old man with a large family to feed, of weak health and poor. Is there any help to overcome my difficulties?’ The Messenger of Allah, O Allah, grant compensation to Muhammad and his family worthy of their services to Your cause, looked to his companions and his companions looked at him. He said, ‘He made us and you to hear his words.’ A man then stood up and said, ‘Yesterday I was like you.’ He then took him to his house and gave him a bar of gold that they used instead of currency for buying and selling. The old man then asked, ‘Is all this for me?’ He said, ‘Yes, all of it is for you.’ The old man said, ‘I accept your bar of gold, but I am not a Jinny or a human being. I am a messenger of Allah to test you. I have found you a thankful person. May Allah grant you good reward.’” "
        ]
      }
    },
    "verse_translations": [
      "en.hubeali",
      "en.sarwar"
    ]
  },
  "index": "al-kafi:4:1:37:11",
  "kind": "verse_detail"
}