{
  "data": {
    "chapter_path": "/books/al-kafi:7:2:36",
    "chapter_title": {
      "ar": "باب مَوَارِيثِ الْقَتْلَى وَ مَنْ يَرِثُ مِنَ الدِّيَةِ وَ مَنْ لَا يَرِثُ",
      "en": "Chapter 34 – Inheritances of the murdered, and who would inherit from the wergild (blood money compensation), and who would not inherit"
    },
    "gradings": [
      "Allamah Baqir al-Majlisi: <span> صحيح على الظاهر    </span> - Mir‘at al ‘Uqul Fi Sharh Akhbar Al al Rasul (23/207)"
    ],
    "nav": {
      "next": "/books/al-kafi:7:2:36:6",
      "prev": "/books/al-kafi:7:2:36:4",
      "up": "/books/al-kafi:7:2:36"
    },
    "verse": {
      "gradings": [
        "Allamah Baqir al-Majlisi: <span> صحيح على الظاهر    </span> - Mir‘at al ‘Uqul Fi Sharh Akhbar Al al Rasul (23/207)"
      ],
      "index": 13479,
      "local_index": 5,
      "narrator_chain": {
        "parts": [
          {
            "kind": "narrator",
            "path": "/people/narrators/37",
            "text": "عَلِيُّ بْنُ إِبْرَاهِيمَ"
          },
          {
            "kind": "plain",
            "text": " عَنْ "
          },
          {
            "kind": "narrator",
            "path": "/people/narrators/107",
            "text": "مُحَمَّدِ بْنِ عِيسَى"
          },
          {
            "kind": "plain",
            "text": " عَنْ "
          },
          {
            "kind": "narrator",
            "path": "/people/narrators/151",
            "text": "يُونُسَ"
          },
          {
            "kind": "plain",
            "text": " عَنْ "
          },
          {
            "kind": "narrator",
            "path": "/people/narrators/266",
            "text": "عَاصِمِ بْنِ حُمَيْدٍ"
          },
          {
            "kind": "plain",
            "text": " عَنْ "
          },
          {
            "kind": "narrator",
            "path": "/people/narrators/1661",
            "text": "مُحَمَّدِ بْنِ قَيْسٍ"
          },
          {
            "kind": "plain",
            "text": " عَنْ "
          },
          {
            "kind": "narrator",
            "path": "/people/narrators/8",
            "text": "أَبِي جَعْفَرٍ ( عليه السلام )"
          },
          {
            "kind": "plain",
            "text": " قَالَ"
          }
        ]
      },
      "part_type": "Hadith",
      "path": "/books/al-kafi:7:2:36:5",
      "text": [
        " قَالَ الدِّيَةُ يَرِثُهَا الْوَرَثَةُ عَلَى فَرَائِضِ الْمَوَارِيثِ إِلَّا الْإِخْوَةَ مِنَ الْأُمِّ فَإِنَّهُمْ لَا يَرِثُونَ مِنَ الدِّيَةِ شَيْئاً ."
      ],
      "translations": {
        "en.hubeali": [
          "Ali Bin Ibrahim, from Muhammad Bin Isa, from Yunus, from Aasim Bin Humeyd, from Muhammad Bin Qays, ",
          "(It has been narrated) from Abu Ja’far<sup>asws</sup> having said: ‘The wergild, the inheritors would inherit it upon the Obligated inheritances except the brothers from the mother, so they would not be inheriting anything from the wergild’."
        ],
        "en.sarwar": [
          "5. Ali ibn Ibrahim has narrated from Muhammad ibn ‘Isa from Yunus from ‘Asem ibn Hakim from Muhammad ibn Qays who has narrated the following: “Abu Ja’far, ‘Alayhi al-Salam, has said, ’From the wergild the heirs receive according to their ordained shares except brothers and sisters from the mother’s side who do not inherit anything thereof.’” "
        ]
      }
    }
  },
  "index": "al-kafi:7:2:36:5",
  "kind": "verse_detail"
}