{
  "data": {
    "index": 3246,
    "path": "/people/narrators/3246",
    "subchains": {
      "20-4-5-387-7-3246": {
        "narrator_ids": [
          20,
          4,
          5,
          387,
          7,
          3246
        ],
        "verse_paths": [
          "/books/al-kafi:3:5:46:7"
        ]
      },
      "20-4-5-387-7-3246-3247": {
        "narrator_ids": [
          20,
          4,
          5,
          387,
          7,
          3246,
          3247
        ],
        "verse_paths": [
          "/books/al-kafi:3:5:46:7"
        ]
      },
      "3246-3247": {
        "narrator_ids": [
          3246,
          3247
        ],
        "verse_paths": [
          "/books/al-kafi:3:5:46:7"
        ]
      },
      "387-7-3246": {
        "narrator_ids": [
          387,
          7,
          3246
        ],
        "verse_paths": [
          "/books/al-kafi:3:5:46:7"
        ]
      },
      "387-7-3246-3247": {
        "narrator_ids": [
          387,
          7,
          3246,
          3247
        ],
        "verse_paths": [
          "/books/al-kafi:3:5:46:7"
        ]
      },
      "4-5-387-7-3246": {
        "narrator_ids": [
          4,
          5,
          387,
          7,
          3246
        ],
        "verse_paths": [
          "/books/al-kafi:3:5:46:7"
        ]
      },
      "4-5-387-7-3246-3247": {
        "narrator_ids": [
          4,
          5,
          387,
          7,
          3246,
          3247
        ],
        "verse_paths": [
          "/books/al-kafi:3:5:46:7"
        ]
      },
      "5-387-7-3246": {
        "narrator_ids": [
          5,
          387,
          7,
          3246
        ],
        "verse_paths": [
          "/books/al-kafi:3:5:46:7"
        ]
      },
      "5-387-7-3246-3247": {
        "narrator_ids": [
          5,
          387,
          7,
          3246,
          3247
        ],
        "verse_paths": [
          "/books/al-kafi:3:5:46:7"
        ]
      },
      "7-3246": {
        "narrator_ids": [
          7,
          3246
        ],
        "verse_paths": [
          "/books/al-kafi:3:5:46:7"
        ]
      },
      "7-3246-3247": {
        "narrator_ids": [
          7,
          3246,
          3247
        ],
        "verse_paths": [
          "/books/al-kafi:3:5:46:7"
        ]
      }
    },
    "titles": {
      "ar": "أَبِي جَعْفَرٍ ( عليه السلام ) فِي أَهْلِ الْجِزْيَةِ يُؤْخَذُ مِنْ أَمْوَالِهِمْ"
    },
    "verse_paths": [
      "/books/al-kafi:3:5:46:7"
    ]
  },
  "index": 3246,
  "kind": "person_content"
}