{
  "data": {
    "index": 378,
    "path": "/people/narrators/378",
    "subchains": {
      "10-378": {
        "narrator_ids": [
          10,
          378
        ],
        "verse_paths": [
          "/books/al-kafi:1:3:10:4"
        ]
      },
      "10-378-379": {
        "narrator_ids": [
          10,
          378,
          379
        ],
        "verse_paths": [
          "/books/al-kafi:1:3:10:4"
        ]
      },
      "378-379": {
        "narrator_ids": [
          378,
          379
        ],
        "verse_paths": [
          "/books/al-kafi:1:3:10:4"
        ]
      },
      "75-10-378": {
        "narrator_ids": [
          75,
          10,
          378
        ],
        "verse_paths": [
          "/books/al-kafi:1:3:10:4"
        ]
      },
      "75-10-378-379": {
        "narrator_ids": [
          75,
          10,
          378,
          379
        ],
        "verse_paths": [
          "/books/al-kafi:1:3:10:4"
        ]
      },
      "9-75-10-378": {
        "narrator_ids": [
          9,
          75,
          10,
          378
        ],
        "verse_paths": [
          "/books/al-kafi:1:3:10:4"
        ]
      },
      "9-75-10-378-379": {
        "narrator_ids": [
          9,
          75,
          10,
          378,
          379
        ],
        "verse_paths": [
          "/books/al-kafi:1:3:10:4"
        ]
      }
    },
    "titles": {
      "ar": "أَحْمَدَ بْنِ بَشِيرٍ الْبَرْقِيِّ"
    },
    "verse_paths": [
      "/books/al-kafi:1:3:10:4"
    ]
  },
  "index": 378,
  "kind": "person_content"
}