{
  "data": {
    "chapter_path": "/books/quran:37",
    "chapter_title": {
      "ar": "الصافات",
      "en": "Those drawn up in Ranks",
      "ent": "As-Saaffaat"
    },
    "nav": {
      "next": "/books/quran:37:43",
      "prev": "/books/quran:37:41",
      "up": "/books/quran:37"
    },
    "verse": {
      "index": 3830,
      "local_index": 42,
      "part_type": "Verse",
      "path": "/books/quran:37:42",
      "relations": {
        "Mentioned In": [
          "/books/al-kafi:8:1:24:1"
        ]
      },
      "text": [
        "فَوَاکِهُ‌ وَ هُمْ‌ مُکْرَمُونَ‌"
      ],
      "translations": {
        "en.ahmedali": [
          "Fruits of every kind, and they will be honoured"
        ],
        "en.ahmedraza": [
          "Fruits; and they will be honoured."
        ],
        "en.arberry": [
          "fruits -- and they high-honoured"
        ],
        "en.daryabadi": [
          "Fruits! And they shall be honoured."
        ],
        "en.hilali": [
          "Fruits; and they shall be honoured,"
        ],
        "en.itani": [
          "Fruits; and they will be honored."
        ],
        "en.maududi": [
          "a variety of delicious fruits; and they shall be honoured"
        ],
        "en.mubarakpuri": [
          "Fruits; and they shall be honored,"
        ],
        "en.pickthall": [
          "Fruits. And they will be honoured"
        ],
        "en.qarai": [
          "—fruits—and they will be held in honour,"
        ],
        "en.qaribullah": [
          "fruits. And they are receivers of generosity"
        ],
        "en.sahih": [
          "Fruits; and they will be honored"
        ],
        "en.sarwar": [
          "and fruits while they are honored."
        ],
        "en.shakir": [
          "Fruits, and they shall be highly honored,"
        ],
        "en.transliteration": [
          "Faw<u>a</u>kihu wahum mukramoon<b>a</b>"
        ],
        "en.wahiduddin": [
          "fruits of various kinds; and they shall be honoured,"
        ],
        "en.yusufali": [
          "Fruits (Delights); and they (shall enjoy) honour and dignity,"
        ],
        "fa.ansarian": [
          "میوه هایی [گوناگون] در حالی که مورد اکرام خواهند بود،"
        ],
        "fa.ayati": [
          "از ميوه‌ها، و گرامى داشتگانند؛"
        ],
        "fa.bahrampour": [
          "[انواع‌] ميوه‌ها و آنها گرامى داشتگانند"
        ],
        "fa.fooladvand": [
          "[انواع‌] ميوه‌ها! و آنان مورد احترام خواهند بود."
        ],
        "fa.ghomshei": [
          "میوه‌های گوناگون بهشتی، و هم آنها (در آن عالم جاودانی) بزرگوار و محترمند."
        ],
        "fa.khorramdel": [
          "یعنی میوه‌های رنگارنگ. و آنان مکرّم و معزّزند (و با نهایت احترام از ایشان پذیرائی می‌گردد). [[«فَوَاکِهُ»: بدل از (رزق) است. تنکیر آن دالّ بر وفور و مرغوبیّت است. «مُکْرَمُونَ»: اشاره به این است که همچون حیوانات، آذوقه در مقابل آنان ریخته نمی‌شود، بلکه همچون مهمانان عزیزی، از ایشان پذیرائی می‌گردد.]]"
        ],
        "fa.khorramshahi": [
          "انواع میوه‌ها، و خود گرامیانند"
        ],
        "fa.makarem": [
          "میوه‌ها (ی گوناگون پر ارزش)، و آنها گرامی داشته می‌شوند..."
        ],
        "fa.moezzi": [
          "میوه‌هائی و آنانند گرامی‌داشتگان‌"
        ],
        "fa.mojtabavi": [
          "ميوه‌ها [از هر گونه‌]، و ايشان گرامى‌داشتگان و نواختگانند،"
        ],
        "fa.sadeqi": [
          "(از انواع) میوه‌ها! حال آنکه آنان گرامی‌شدگانند."
        ]
      }
    },
    "verse_translations": [
      "fa.ansarian",
      "fa.ayati",
      "fa.bahrampour",
      "fa.fooladvand",
      "fa.ghomshei",
      "fa.khorramdel",
      "fa.khorramshahi",
      "fa.makarem",
      "fa.moezzi",
      "fa.mojtabavi",
      "fa.sadeqi",
      "en.ahmedali",
      "en.ahmedraza",
      "en.arberry",
      "en.daryabadi",
      "en.hilali",
      "en.itani",
      "en.maududi",
      "en.mubarakpuri",
      "en.pickthall",
      "en.qarai",
      "en.qaribullah",
      "en.sahih",
      "en.sarwar",
      "en.shakir",
      "en.transliteration",
      "en.wahiduddin",
      "en.yusufali"
    ]
  },
  "index": "quran:37:42",
  "kind": "verse_detail"
}