{
  "data": {
    "chapter_path": "/books/tahdhib-al-ahkam:5:22",
    "chapter_title": {
      "ar": "22 - بَابُ اَلْوَدَاعِ"
    },
    "nav": {
      "next": "/books/tahdhib-al-ahkam:5:22:2",
      "up": "/books/tahdhib-al-ahkam:5:22"
    },
    "verse": {
      "index": 5805,
      "local_index": 1,
      "narrator_chain": {
        "parts": [
          {
            "kind": "narrator",
            "path": "/people/narrators/21",
            "text": "اَلْحُسَيْنُ بْنُ سَعِيدٍ"
          },
          {
            "kind": "plain",
            "text": " عَنْ "
          },
          {
            "kind": "narrator",
            "path": "/people/narrators/38",
            "text": "حَمَّادِ بْنِ عِيسَى"
          },
          {
            "kind": "plain",
            "text": " عَنْ "
          },
          {
            "kind": "narrator",
            "path": "/people/narrators/69",
            "text": "فَضَالَةَ بْنِ أَيُّوبَ"
          },
          {
            "kind": "plain",
            "text": " عَنْ "
          },
          {
            "kind": "narrator",
            "path": "/people/narrators/45",
            "text": "مُعَاوِيَةَ بْنِ عَمَّارٍ"
          },
          {
            "kind": "plain",
            "text": " عَنْ "
          },
          {
            "kind": "plain",
            "text": "أَبِي عَبْدِ اَللَّهِ عَلَيْهِ اَلسَّلاَمُ"
          },
          {
            "kind": "plain",
            "text": " قَالَ"
          }
        ]
      },
      "part_type": "Hadith",
      "path": "/books/tahdhib-al-ahkam:5:22:1",
      "text": [
        " : «إِذَا أَرَدْتَ أَنْ تَخْرُجَ مِنْ مَكَّةَ فَتَأْتِيَ أَهْلَكَ فَوَدِّعِ اَلْبَيْتَ وَ طُفْ أُسْبُوعاً وَ إِنِ اِسْتَطَعْتَ أَنْ تَسْتَلِمَ اَلْحَجَرَ اَلْأَسْوَدَ وَ اَلرُّكْنَ اَلْيَمَانِيَّ فِي كُلِّ شَوْطٍ فَافْعَلْ وَ إِلاَّ فَافْتَحْ بِهِ وَ اِخْتِمْ بِهِ وَ إِنْ لَمْ تَسْتَطِعْ ذَلِكَ فَمُوَسَّعٌ عَلَيْكَ ثُمَّ تَأْتِي اَلْمُسْتَجَارَ فَتَصْنَعُ عِنْدَهُ مِثْلَ مَا صَنَعْتَ يَوْمَ قَدِمْتَ مَكَّةَ ثُمَّ تَخَيَّرْ لِنَفْسِكَ مِنَ اَلدُّعَاءِ ثُمَّ اِسْتَلِمِ اَلْحَجَرَ اَلْأَسْوَدَ ثُمَّ أَلْصِقْ بَطْنَكَ بِالْبَيْتِ وَ اِحْمَدِ اَللَّهَ وَ أَثْنِ عَلَيْهِ وَ صَلِّ عَلَى مُحَمَّدٍ وَ آلِهِ ثُمَّ قُلِ اَللَّهُمَّ صَلِّ عَلَى مُحَمَّدٍ عَبْدِكَ وَ رَسُولِكَ وَ أَمِينِكَ وَ حَبِيبِكَ وَ نَجِيبِكَ وَ خِيَرَتِكَ مِنْ خَلْقِكَ اَللَّهُمَّ كَمَا بَلَّغَ رِسَالَتَكَ وَ جَاهَدَ فِي سَبِيلِكَ وَ صَدَعَ بِأَمْرِكَ وَ أُوذِيَ فِيكَ وَ فِي جَنْبِكَ حَتَّى أَتَاهُ اَلْيَقِينُ اَللَّهُمَّ اِقْلِبْنِي مُفْلِحاً مُنْجِحاً مُسْتَجَاباً لِي بِأَفْضَلِ مَا يَرْجِعُ بِهِ أَحَدٌ مِنْ وَفْدِكَ مِنَ اَلْمَغْفِرَةِ وَ اَلْبَرَكَةِ وَ اَلرِّضْوَانِ وَ اَلْعَافِيَةِ مِمَّا يَسَعُنِي أَنْ أَطْلُبَ أَنْ تُعْطِيَنِي مِثْلَ اَلَّذِي أَعْطَيْتَهُ أَفْضَلَ مَنْ عِنْدَكَ وَ تَزِيدَنِي عَلَيْهِ اَللَّهُمَّ إِنْ أَمَتَّنِي فَاغْفِرْ لِي وَ إِنْ أَحْيَيْتَنِي فَارْزُقْنِيهِ مِنْ قَابِلٍ اَللَّهُمَّ لاَ تَجْعَلْهُ آخِرَ اَلْعَهْدِ مِنْ بَيْتِكَ اَللَّهُمَّ إِنِّي عَبْدُكَ وَ اِبْنُ عَبْدِكَ وَ اِبْنُ أَمَتِكَ حَمَلْتَنِي عَلَى دَابَّتِكَ وَ سَيَّرْتَنِي فِي بِلاَدِكَ حَتَّى أَدْخَلْتَنِي حَرَمَكَ وَ أَمْنَكَ وَ قَدْ كَانَ فِي حُسْنِ ظَنِّي بِكَ أَنْ تَغْفِرَ لِي ذُنُوبِي فَإِنْ كُنْتَ قَدْ غَفَرْتَ لِي ذُنُوبِي فَازْدَدْ عَنِّي رِضًا وَ قَرِّبْنِي إِلَيْكَ زُلْفَى وَ لاَ تُبَاعِدْنِي وَ إِنْ كُنْتَ لَمْ تَغْفِرْ لِي فَمِنَ اَلْآنَ فَاغْفِرْ لِي قَبْلَ أَنْ تَنْأَى عَنْ بَيْتِكَ دَارِي وَ هَذَا أَوَانُ اِنْصِرَافِي إِنْ كُنْتَ أَذِنْتَ لِي فَغَيْرُ رَاغِبٍ عَنْكَ وَ لاَ عَنْ بَيْتِكَ وَ لاَ مُسْتَبْدِلٍ بِكَ وَ لاَ بِهِ اَللَّهُمَّ اِحْفَظْنِي مِنْ بَيْنِ يَدَيَّ وَ مِنْ خَلْفِي وَ عَنْ يَمِينِي وَ عَنْ شِمَالِي حَتَّى تُبْلِغَنِي أَهْلِي وَ اِكْفِنِي مَئُونَةَ عِبَادِكَ وَ عِيَالِي فَإِنَّكَ وَلِيُّ ذَلِكَ مِنْ خَلْقِكَ وَ مِنِّي ثُمَّ اِئْتِ زَمْزَمَ فَاشْرَبْ مِنْهَا ثُمَّ اُخْرُجْ فَقُلْ آئِبُونَ تَائِبُونَ عَائِدُونَ لِرَبِّنَا حَامِدُونَ «إِلى رَبِّنا راغِبُونَ » إِلَى رَبِّنَا رَاجِعُونَ » فَإِنَّ أَبَا عَبْدِ اَللَّهِ عَلَيْهِ اَلسَّلاَمُ لَمَّا أَنْ وَدَّعَهَا وَ أَرَادَ أَنْ يَخْرُجَ مِنَ اَلْمَسْجِدِ خَرَّ سَاجِداً عِنْدَ بَابِ اَلْمَسْجِدِ طَوِيلاً ثُمَّ قَامَ فَخَرَجَ ."
      ]
    }
  },
  "index": "tahdhib-al-ahkam:5:22:1",
  "kind": "verse_detail"
}