{
  "data": {
    "chapter_path": "/books/man-la-yahduruhu-al-faqih:3:1:5",
    "chapter_title": {
      "en": "Chapter on Conditional Emancipation (tadbir)"
    },
    "nav": {
      "next": "/books/man-la-yahduruhu-al-faqih:3:1:5:5",
      "prev": "/books/man-la-yahduruhu-al-faqih:3:1:5:3",
      "up": "/books/man-la-yahduruhu-al-faqih:3:1:5"
    },
    "source_url": "https://thaqalayn.net/hadith/34/1/47/4",
    "verse": {
      "index": 1735,
      "local_index": 4,
      "part_type": "Hadith",
      "path": "/books/man-la-yahduruhu-al-faqih:3:1:5:4",
      "source_url": "https://thaqalayn.net/hadith/34/1/47/4",
      "text": [
        "3459 - وَ سُئِلَ أَبُو إِبْرَاهِيمَ عَلَيْهِ اَلسَّلاَمُ عَنِ اِمْرَأَةٍ دَبَّرَتْ جَارِيَةً لَهَا فَوَلَدَتِ اَلْجَارِيَةُ جَارِيَةً نَفِيسَةً فَلَمْ يُدْرَ أَ مُدَبَّرَةٌ هِيَ مِثْلُ أُمِّهَا أَمْ لاَ فَقَالَ \"مَتَى كَانَ اَلْحَمْلُ كَانَ وَ هِيَ مُدَبَّرَةٌ أَوْ قَبْلَ اَلتَّدْبِيرِ\" قُلْتُ جُعِلْتُ فِدَاكَ لاَ أَدْرِي أَجِبْنِي فِيهِمَا جَمِيعاً فَقَالَ \"إِنْ كَانَتِ اَلْجَارِيَةُ حُبْلَى قَبْلَ اَلتَّدْبِيرِ وَ لَمْ يَذْكُرْ مَا فِي بَطْنِهَا فَالْجَارِيَةُ مُدَبَّرَةٌ وَ مَا فِي بَطْنِهَا رِقٌّ وَ إِنْ كَانَ اَلتَّدْبِيرُ قَبْلَ اَلْحَمْلِ ثُمَّ حَدَثَ اَلْحَمْلُ فَالْوَلَدُ مُدَبَّرٌ مَعَ أُمِّهِ لِأَنَّ اَلْحَمْلَ إِنَّمَا حَدَثَ بَعْدَ اَلتَّدْبِيرِ\"."
      ],
      "translations": {
        "en.bab-ul-qaim-publications": [
          "Hadith.3459 - Abu Ibrahim (Imam Musa ibn Jafar Al-Kadhim (as)) was asked about a woman who made her bondwoman mudabbar (to be freed after her death). The bondwoman later gave birth to a precious daughter, and it was unclear whether the child was also mudabbar like her mother or not.\nImam (as) said: \"When the pregnancy occurred, was it before or after the tadbir (declaration of delayed emancipation)?\"\nI said: \"May I be your ransom, I do not know. Please answer regarding both situations.\"\nImam (as) said: \"If the bondwoman was pregnant before the tadbir and her pregnancy was not mentioned during the declaration, then the bondwoman is mudabbar, but what is in her womb remains in bondage (not mudabbar).\nHowever, if the tadbir occurred before the pregnancy and then she became pregnant, the child is mudabbar along with her, because the pregnancy occurred after the tadbir.\""
        ]
      }
    }
  },
  "index": "man-la-yahduruhu-al-faqih:3:1:5:4",
  "kind": "verse_detail"
}