{
  "data": {
    "chapter_path": "/books/tahdhib-al-ahkam:1:39",
    "chapter_title": {
      "ar": "23 - بَابُ تَلْقِينِ اَلْمُحْتَضَرِينَ"
    },
    "nav": {
      "next": "/books/tahdhib-al-ahkam:1:39:8",
      "prev": "/books/tahdhib-al-ahkam:1:39:6",
      "up": "/books/tahdhib-al-ahkam:1:39"
    },
    "verse": {
      "index": 1393,
      "local_index": 7,
      "narrator_chain": {
        "parts": [
          {
            "kind": "plain",
            "text": "7- "
          },
          {
            "kind": "narrator",
            "path": "/people/narrators/4134",
            "text": "مُحَمَّدُ بْنُ أَحْمَدَ بْنِ يَحْيَى"
          },
          {
            "kind": "plain",
            "text": " عَنْ "
          },
          {
            "kind": "narrator",
            "path": "/people/narrators/60",
            "text": "رَجُلٍ"
          },
          {
            "kind": "plain",
            "text": " عَنِ "
          },
          {
            "kind": "narrator",
            "path": "/people/narrators/1385",
            "text": "اَلْمِسْمَعِيِّ"
          },
          {
            "kind": "plain",
            "text": " عَنْ "
          },
          {
            "kind": "narrator",
            "path": "/people/narrators/622",
            "text": "إِسْمَاعِيلَ بْنِ يَسَارٍ"
          },
          {
            "kind": "plain",
            "text": " عَنْ "
          },
          {
            "kind": "narrator",
            "path": "/people/narrators/85",
            "text": "يُونُسَ بْنِ يَعْقُوبَ"
          },
          {
            "kind": "plain",
            "text": " عَنْ "
          },
          {
            "kind": "plain",
            "text": "أَبِي عَبْدِ اَللَّهِ عَلَيْهِ اَلسَّلاَمُ"
          },
          {
            "kind": "plain",
            "text": " قَالَ"
          }
        ]
      },
      "part_type": "Hadith",
      "path": "/books/tahdhib-al-ahkam:1:39:7",
      "text": [
        " : «لاَ تَحْضُرُ اَلْحَائِضُ اَلْمَيِّتَ وَ لاَ اَلْجُنُبُ عِنْدَ اَلتَّلْقِينِ وَ لاَ بَأْسَ أَنْ يَلِيَا غُسْلَهُ »."
      ]
    }
  },
  "index": "tahdhib-al-ahkam:1:39:7",
  "kind": "verse_detail"
}